{
  "$schema": "https://developer.microsoft.com/json-schemas/fabric/item/report/definition/visualContainer/2.7.0/schema.json",
  "name": "829b914102d518523ee0",
  "position": {
    "x": 692,
    "y": 0,
    "z": 2000,
    "height": 185,
    "width": 588,
    "tabOrder": 0
  },
  "visual": {
    "visualType": "pivotTable",
    "query": {
      "queryState": {
        "Columns": {
          "projections": [
            {
              "field": {
                "Column": {
                  "Expression": {
                    "SourceRef": {
                      "Entity": "products_fact"
                    }
                  },
                  "Property": "Products"
                }
              },
              "queryRef": "products_fact.Products",
              "nativeQueryRef": "Products",
              "active": true
            }
          ]
        },
        "Rows": {
          "projections": [
            {
              "field": {
                "Column": {
                  "Expression": {
                    "SourceRef": {
                      "Entity": "campaign_fact"
                    }
                  },
                  "Property": "Campaign"
                }
              },
              "queryRef": "campaign_fact.Campaign",
              "nativeQueryRef": "Campaign",
              "active": true
            }
          ]
        },
        "Values": {
          "projections": [
            {
              "field": {
                "Aggregation": {
                  "Expression": {
                    "Column": {
                      "Expression": {
                        "SourceRef": {
                          "Entity": "products_fact"
                        }
                      },
                      "Property": "Total_Product_Sales"
                    }
                  },
                  "Function": 0
                }
              },
              "queryRef": "Sum(products_fact.Total_Product_Sales)",
              "nativeQueryRef": "Sum of Total_Product_Sales"
            }
          ]
        }
      },
      "sortDefinition": {
        "sort": [
          {
            "field": {
              "Column": {
                "Expression": {
                  "SourceRef": {
                    "Entity": "campaign_fact"
                  }
                },
                "Property": "Campaign"
              }
            },
            "direction": "Ascending"
          }
        ]
      }
    },
    "drillFilterOtherVisuals": true
  },
  "filterConfig": {
    "filters": [
      {
        "name": "c87f89740dcdce039933",
        "field": {
          "Column": {
            "Expression": {
              "SourceRef": {
                "Entity": "campaign_fact"
              }
            },
            "Property": "Accepted"
          }
        },
        "type": "Advanced",
        "filter": {
          "Version": 2,
          "From": [
            {
              "Name": "c",
              "Entity": "campaign_fact",
              "Type": 0
            }
          ],
          "Where": [
            {
              "Condition": {
                "Comparison": {
                  "ComparisonKind": 0,
                  "Left": {
                    "Column": {
                      "Expression": {
                        "SourceRef": {
                          "Source": "c"
                        }
                      },
                      "Property": "Accepted"
                    }
                  },
                  "Right": {
                    "Literal": {
                      "Value": "1L"
                    }
                  }
                }
              }
            }
          ]
        },
        "howCreated": "User"
      }
    ]
  }
}